inputCode/csc.csv
inputCode/hsdd2.csv
inputCode/test.csv
inputCode/Batch/CSC_v0.70d1.45.csv
inputCode/Batch/CSC_v0.80d1.50.csv
inputCode/Batch/CSC_v0.85d1.50.csv
inputCode/Batch/RGNJL_v0.70d1.45.csv
inputCode/Batch/RGNJL_v0.80d1.50.csv
inputCode/Batch/RGNJL_v0.85d1.50.csv
inputRaw/csc.csv
inputRaw/hsdd2.csv
inputRaw/test.csv
inputRaw/batch/CSC_v0.70d1.45.csv
inputRaw/batch/CSC_v0.80d1.50.csv
inputRaw/batch/CSC_v0.85d1.50.csv
inputRaw/batch/RGNJL_v0.70d1.45.csv
inputRaw/batch/RGNJL_v0.80d1.50.csv
inputRaw/batch/RGNJL_v0.85d1.50.csv
tovextravaganza/__init__.py
tovextravaganza/cli/__init__.py
tovextravaganza/cli/converter.py
tovextravaganza/cli/radial.py
tovextravaganza/cli/tov.py
tovextravaganza/core/__init__.py
tovextravaganza/core/eos.py
tovextravaganza/core/output_handlers.py
tovextravaganza/core/tidal_calculator.py
tovextravaganza/core/tov_solver.py
tovextravaganza/utils/__init__.py
tovextravaganza/utils/demo.py
tovextravaganza/utils/help_command.py
tovextravaganza/utils/read_radial_hdf5.py
tovextravaganza/utils/timeout.py
tovextravaganza/utils/wizard.py
tovextravaganza-1.5.2.dist-info/licenses/LICENSE
tovextravaganza-1.5.2.dist-info/METADATA
tovextravaganza-1.5.2.dist-info/WHEEL
tovextravaganza-1.5.2.dist-info/entry_points.txt
tovextravaganza-1.5.2.dist-info/top_level.txt
tovextravaganza-1.5.2.dist-info/RECORD
