Metadata-Version: 2.4
Name: tovextravaganza
Version: 1.5.2
Summary: Python toolkit for solving TOV equations, calculating tidal deformability, and exploring neutron star properties for gravitational wave and nuclear astrophysics research
Home-page: https://github.com/PsiPhiDelta/TOVExtravaganza
Author: Hosein Gholami
Author-email: Hosein Gholami <mohogholami@gmail.com>
License: MIT
Project-URL: Homepage, https://github.com/PsiPhiDelta/TOVExtravaganza
Project-URL: Documentation, https://github.com/PsiPhiDelta/TOVExtravaganza#readme
Project-URL: Repository, https://github.com/PsiPhiDelta/TOVExtravaganza
Project-URL: Source Code, https://github.com/PsiPhiDelta/TOVExtravaganza
Project-URL: Bug Reports, https://github.com/PsiPhiDelta/TOVExtravaganza/issues
Project-URL: Changelog, https://github.com/PsiPhiDelta/TOVExtravaganza/blob/main/CHANGELOG.md
Project-URL: arXiv Paper, https://arxiv.org/abs/2411.04064
Project-URL: Cite, https://github.com/PsiPhiDelta/TOVExtravaganza/blob/main/CITATION.cff
Keywords: neutron-stars,neutron-star,tov,tov-equations,tov-equation,equation-of-state,eos,tidal-deformability,gravitational-waves,astrophysics,astronomy,compact-objects,GW170817,love-number,mass-radius,general-relativity,nuclear-physics,nuclear-astrophysics,stellar-structure,binary-neutron-stars,ligo,virgo,python-physics,computational-astrophysics,color-superconductivity,superconductivity,csc,cfl,quark-matter,dense-matter,phase-transitions,qcd,relativistic-stars,computational-physics,scientific-
Classifier: Development Status :: 5 - Production/Stable
Classifier: Intended Audience :: Science/Research
Classifier: Topic :: Scientific/Engineering :: Physics
Classifier: Topic :: Scientific/Engineering :: Astronomy
Classifier: License :: OSI Approved :: MIT License
Classifier: Programming Language :: Python :: 3
Classifier: Programming Language :: Python :: 3.7
Classifier: Programming Language :: Python :: 3.8
Classifier: Programming Language :: Python :: 3.9
Classifier: Programming Language :: Python :: 3.10
Classifier: Programming Language :: Python :: 3.11
Classifier: Programming Language :: Python :: 3.12
Requires-Python: >=3.7
License-File: LICENSE
Requires-Dist: numpy>=1.19.0
Requires-Dist: scipy>=1.5.0
Requires-Dist: matplotlib>=3.3.0
Provides-Extra: dev
Requires-Dist: pytest>=6.0; extra == "dev"
Requires-Dist: pytest-cov>=2.0; extra == "dev"
Provides-Extra: hdf5
Requires-Dist: h5py>=3.0; extra == "hdf5"
Provides-Extra: all
Requires-Dist: h5py>=3.0; extra == "all"
Dynamic: author
Dynamic: home-page
Dynamic: license-file
Dynamic: requires-python
